django_psdb_engine/__init__.py
django_psdb_engine/base.py
django_psdb_engine/features.py
django_psdb_engine-1.0.6.dist-info/LICENSE
django_psdb_engine-1.0.6.dist-info/METADATA
django_psdb_engine-1.0.6.dist-info/WHEEL
django_psdb_engine-1.0.6.dist-info/top_level.txt
django_psdb_engine-1.0.6.dist-info/RECORD
