Metadata-Version: 2.1
Name: django_psdb_engine
Version: 1.0.6
Summary: Django PlanetScale database engine.
Home-page: https://github.com/lnxpy/django-psdb-engine
Author: Sadra Yahyapour
Author-email: lnxpylnxpy@gmail.com
License: MIT license
Keywords: django_psdb_engine,planetscale,django,engine,database
Classifier: Development Status :: 2 - Pre-Alpha
Classifier: Intended Audience :: Developers
Classifier: License :: OSI Approved :: MIT License
Classifier: Natural Language :: English
Classifier: Programming Language :: Python :: 3
Classifier: Programming Language :: Python :: 3.6
Classifier: Programming Language :: Python :: 3.7
Classifier: Programming Language :: Python :: 3.8
Requires-Python: >=3.6
License-File: LICENSE
